{
  "_format": "hh-sol-cache-2",
  "files": {
    "D:\\Work\\practice\\hardhat_dev\\contracts\\myVideo.sol": {
      "lastModificationDate": 1723744010372,
      "contentHash": "fbd366fb1b654a1d96ba93cc44c425a2",
      "sourceName": "contracts/myVideo.sol",
      "solcConfig": {
        "version": "0.8.24",
        "settings": {
          "evmVersion": "paris",
          "optimizer": {
            "enabled": false,
            "runs": 200
          },
          "outputSelection": {
            "*": {
              "*": [
                "abi",
                "evm.bytecode",
                "evm.deployedBytecode",
                "evm.methodIdentifiers",
                "metadata"
              ],
              "": [
                "ast"
              ]
            }
          }
        }
      },
      "imports": [],
      "versionPragmas": [
        "^0.8.24"
      ],
      "artifacts": [
        "MyVideo"
      ]
    }
  }
}
